[
  {
    "filtered": 126000, 
    "direction": "FortyFiveUp", 
    "noise": 1, 
    "raw": 135, 
    "type": "sgv", 
    "_id": "56c7d59fa3f298555f026bea", 
    "sysTime": "2016-02-19T18:53:39.597-0800", 
    "dateString": "2016-02-19T18:53:39.597-0800", 
    "sgv": 126, 
    "device": "xDrip-DexcomShare", 
    "xDrip_filtered": 126, 
    "unfiltered": 132000, 
    "xDrip_raw": 132, 
    "date": 1455936819597, 
    "rssi": 100, 
    "xDrip_calculated_current_slope": 1.6653898677680444e-05, 
    "xDrip_age_adjusted_raw_value": 132, 
    "xDrip_calculated_value": 126
  }, 
  {
    "filtered": 121000, 
    "direction": "FortyFiveUp", 
    "noise": 1, 
    "raw": 133, 
    "type": "sgv", 
    "_id": "56c7d421a3f298555f026be9", 
    "sysTime": "2016-02-19T18:48:39.367-0800", 
    "dateString": "2016-02-19T18:48:39.367-0800", 
    "sgv": 121, 
    "device": "xDrip-DexcomShare", 
    "xDrip_filtered": 121, 
    "unfiltered": 129000, 
    "xDrip_raw": 129, 
    "date": 1455936519367, 
    "rssi": 100, 
    "xDrip_calculated_current_slope": 2.670057639869301e-05, 
    "xDrip_age_adjusted_raw_value": 129, 
    "xDrip_calculated_value": 121
  }, 
  {
    "filtered": 115000, 
    "direction": "FortyFiveUp", 
    "noise": 1, 
    "raw": 125, 
    "type": "sgv", 
    "_id": "56c7d2f6a3f298555f026be8", 
    "sysTime": "2016-02-19T18:43:39.748-0800", 
    "dateString": "2016-02-19T18:43:39.748-0800", 
    "sgv": 113, 
    "device": "xDrip-DexcomShare", 
    "xDrip_filtered": 115, 
    "unfiltered": 123000, 
    "xDrip_raw": 123, 
    "date": 1455936219748, 
    "rssi": 100, 
    "xDrip_calculated_current_slope": 2.3304978942286886e-05, 
    "xDrip_age_adjusted_raw_value": 123, 
    "xDrip_calculated_value": 113
  }, 
  {
    "filtered": 108000, 
    "direction": "SingleUp", 
    "noise": 1, 
    "raw": 122, 
    "type": "sgv", 
    "_id": "56c7d1eaa3f298555f026be7", 
    "sysTime": "2016-02-19T18:38:39.383-0800", 
    "dateString": "2016-02-19T18:38:39.383-0800", 
    "sgv": 106, 
    "device": "xDrip-DexcomShare", 
    "xDrip_filtered": 108, 
    "unfiltered": 118000, 
    "xDrip_raw": 118, 
    "date": 1455935919383, 
    "rssi": 100, 
    "xDrip_calculated_current_slope": 2.9959754063707752e-05, 
    "xDrip_age_adjusted_raw_value": 118, 
    "xDrip_calculated_value": 106
  }, 
  {
    "filtered": 98000, 
    "direction": "SingleUp", 
    "noise": 1, 
    "raw": 121, 
    "type": "sgv", 
    "_id": "56c7d09ea3f298555f026be3", 
    "sysTime": "2016-02-19T18:33:38.980-0800", 
    "dateString": "2016-02-19T18:33:38.980-0800", 
    "sgv": 97, 
    "device": "xDrip-DexcomShare", 
    "xDrip_filtered": 98, 
    "unfiltered": 112000, 
    "xDrip_raw": 112, 
    "date": 1455935618980, 
    "rssi": 100, 
    "xDrip_calculated_current_slope": 3.672371083082388e-05, 
    "xDrip_age_adjusted_raw_value": 112, 
    "xDrip_calculated_value": 97
  }, 
  {
    "filtered": 90000, 
    "direction": "FortyFiveUp", 
    "noise": 1, 
    "raw": 111, 
    "type": "sgv", 
    "_id": "56c7cf6ca3f298555f026be2", 
    "sysTime": "2016-02-19T18:28:39.446-0800", 
    "dateString": "2016-02-19T18:28:39.446-0800", 
    "sgv": 86, 
    "device": "xDrip-DexcomShare", 
    "xDrip_filtered": 90, 
    "unfiltered": 104000, 
    "xDrip_raw": 104, 
    "date": 1455935319446, 
    "rssi": 100, 
    "xDrip_calculated_current_slope": 4.005407299854804e-05, 
    "xDrip_age_adjusted_raw_value": 104, 
    "xDrip_calculated_value": 86
  }, 
  {
    "filtered": 85000, 
    "direction": "Flat", 
    "noise": 1, 
    "raw": 93, 
    "type": "sgv", 
    "_id": "56c7ce64a3f298555f026be1", 
    "sysTime": "2016-02-19T18:23:39.851-0800", 
    "dateString": "2016-02-19T18:23:39.851-0800", 
    "sgv": 74, 
    "device": "xDrip-DexcomShare", 
    "xDrip_filtered": 85, 
    "unfiltered": 96000, 
    "xDrip_raw": 96, 
    "date": 1455935019851, 
    "rssi": 100, 
    "xDrip_calculated_current_slope": 4.333001136579529e-05, 
    "xDrip_age_adjusted_raw_value": 96, 
    "xDrip_calculated_value": 74
  }, 
  {
    "filtered": 85000, 
    "direction": "Flat", 
    "noise": 1, 
    "raw": 65, 
    "type": "sgv", 
    "_id": "56c7cd18a3f298555f026be0", 
    "sysTime": "2016-02-19T18:18:39.828-0800", 
    "dateString": "2016-02-19T18:18:39.828-0800", 
    "sgv": 61, 
    "device": "xDrip-DexcomShare", 
    "xDrip_filtered": 85, 
    "unfiltered": 88000, 
    "xDrip_raw": 88, 
    "date": 1455934719828, 
    "rssi": 100, 
    "xDrip_calculated_current_slope": 2.329737771372848e-05, 
    "xDrip_age_adjusted_raw_value": 88, 
    "xDrip_calculated_value": 61
  }, 
  {
    "filtered": 88000, 
    "direction": "FortyFiveDown", 
    "noise": 1, 
    "raw": 48, 
    "type": "sgv", 
    "_id": "56c7cbeba3f298555f026bdc", 
    "sysTime": "2016-02-19T18:13:39.365-0800", 
    "dateString": "2016-02-19T18:13:39.365-0800", 
    "sgv": 54, 
    "device": "xDrip-DexcomShare", 
    "xDrip_filtered": 88, 
    "unfiltered": 83000, 
    "xDrip_raw": 83, 
    "date": 1455934419365, 
    "rssi": 100, 
    "xDrip_calculated_current_slope": -1.3332622260146126e-05, 
    "xDrip_age_adjusted_raw_value": 83, 
    "xDrip_calculated_value": 54
  }, 
  {
    "filtered": 94000, 
    "direction": "FortyFiveDown", 
    "noise": 1, 
    "raw": 48, 
    "type": "sgv", 
    "_id": "56c7cadfa3f298555f026bd8", 
    "sysTime": "2016-02-19T18:08:39.349-0800", 
    "dateString": "2016-02-19T18:08:39.349-0800", 
    "sgv": 58, 
    "device": "xDrip-DexcomShare", 
    "xDrip_filtered": 94, 
    "unfiltered": 85000, 
    "xDrip_raw": 85, 
    "date": 1455934119349, 
    "rssi": 100, 
    "xDrip_calculated_current_slope": -2.6633020284374075e-05, 
    "xDrip_age_adjusted_raw_value": 85, 
    "xDrip_calculated_value": 58
  }
]