[
  {
    "filtered": 180000, 
    "direction": "Flat", 
    "noise": 1, 
    "raw": 117, 
    "type": "sgv", 
    "_id": "56c0e37a07f60885b34476ce", 
    "sysTime": "2016-02-14T12:27:13.855-0800", 
    "dateString": "2016-02-14T12:27:13.855-0800", 
    "sgv": 121, 
    "device": "xDrip-DexcomShare", 
    "xDrip_filtered": 180, 
    "unfiltered": 174000, 
    "xDrip_raw": 174, 
    "date": 1455481633855, 
    "rssi": 100, 
    "xDrip_calculated_current_slope": -1.6666666666666667e-05, 
    "xDrip_age_adjusted_raw_value": 174, 
    "xDrip_calculated_value": 121
  }, 
  {
    "filtered": 179000, 
    "direction": "Flat", 
    "noise": 1, 
    "raw": 127, 
    "type": "sgv", 
    "_id": "56c0e37a07f60885b34476cf", 
    "sysTime": "2016-02-14T12:22:13.855-0800", 
    "dateString": "2016-02-14T12:22:13.855-0800", 
    "sgv": 126, 
    "device": "xDrip-DexcomShare", 
    "xDrip_filtered": 179, 
    "unfiltered": 180000, 
    "xDrip_raw": 180, 
    "date": 1455481333855, 
    "rssi": 100, 
    "xDrip_calculated_current_slope": -1.6666666666666667e-05, 
    "xDrip_age_adjusted_raw_value": 180, 
    "xDrip_calculated_value": 126
  }, 
  {
    "filtered": 174000, 
    "direction": "Flat", 
    "noise": 1, 
    "raw": 132, 
    "type": "sgv", 
    "_id": "56c0e0ec07f60885b34476c9", 
    "sysTime": "2016-02-14T12:17:14.439-0800", 
    "dateString": "2016-02-14T12:17:14.439-0800", 
    "sgv": 127, 
    "device": "xDrip-DexcomShare", 
    "xDrip_filtered": 174, 
    "unfiltered": 181000, 
    "xDrip_raw": 181, 
    "date": 1455481034439, 
    "rssi": 100, 
    "xDrip_calculated_current_slope": 1.001950463569081e-05, 
    "xDrip_age_adjusted_raw_value": 181, 
    "xDrip_calculated_value": 127
  }, 
  {
    "filtered": 168000, 
    "direction": "FortyFiveUp", 
    "noise": 1, 
    "raw": 130, 
    "type": "sgv", 
    "_id": "56c0dfd707f60885b34476c5", 
    "sysTime": "2016-02-14T12:12:15.023-0800", 
    "dateString": "2016-02-14T12:12:15.023-0800", 
    "sgv": 124, 
    "device": "xDrip-DexcomShare", 
    "xDrip_filtered": 168, 
    "unfiltered": 176000, 
    "xDrip_raw": 176, 
    "date": 1455480735023, 
    "rssi": 100, 
    "xDrip_calculated_current_slope": 6.668155888148353e-06, 
    "xDrip_age_adjusted_raw_value": 176, 
    "xDrip_calculated_value": 124
  }, 
  {
    "filtered": 160000, 
    "direction": "FortyFiveUp", 
    "noise": 1, 
    "raw": 133, 
    "type": "sgv", 
    "_id": "56c0de8a07f60885b34476c2", 
    "sysTime": "2016-02-14T12:07:15.090-0800", 
    "dateString": "2016-02-14T12:07:15.090-0800", 
    "sgv": 122, 
    "device": "xDrip-DexcomShare", 
    "xDrip_filtered": 160, 
    "unfiltered": 173000, 
    "xDrip_raw": 173, 
    "date": 1455480435090, 
    "rssi": 100, 
    "xDrip_calculated_current_slope": 2.3329756104064043e-05, 
    "xDrip_age_adjusted_raw_value": 173, 
    "xDrip_calculated_value": 122
  }, 
  {
    "filtered": 152000, 
    "direction": "FortyFiveUp", 
    "noise": 1, 
    "raw": 125, 
    "type": "sgv", 
    "_id": "56c0dd5e07f60885b34476c1", 
    "sysTime": "2016-02-14T12:02:15.044-0800", 
    "dateString": "2016-02-14T12:02:15.044-0800", 
    "sgv": 115, 
    "device": "xDrip-DexcomShare", 
    "xDrip_filtered": 152, 
    "unfiltered": 164000, 
    "xDrip_raw": 164, 
    "date": 1455480135044, 
    "rssi": 100, 
    "xDrip_calculated_current_slope": 2.3350379110083694e-05, 
    "xDrip_age_adjusted_raw_value": 164, 
    "xDrip_calculated_value": 115
  }, 
  {
    "filtered": 142000, 
    "direction": "FortyFiveUp", 
    "noise": 1, 
    "raw": 119, 
    "type": "sgv", 
    "_id": "56c0dc8507f60885b34476c0", 
    "sysTime": "2016-02-14T11:57:15.263-0800", 
    "dateString": "2016-02-14T11:57:15.263-0800", 
    "sgv": 108, 
    "device": "xDrip-DexcomShare", 
    "xDrip_filtered": 142, 
    "unfiltered": 156000, 
    "xDrip_raw": 156, 
    "date": 1455479835263, 
    "rssi": 100, 
    "xDrip_calculated_current_slope": 1.9962603389650056e-05, 
    "xDrip_age_adjusted_raw_value": 156, 
    "xDrip_calculated_value": 108
  }, 
  {
    "filtered": 132000, 
    "direction": "FortyFiveUp", 
    "noise": 1, 
    "raw": 114, 
    "type": "sgv", 
    "_id": "56c0dc8507f60885b34476bf", 
    "sysTime": "2016-02-14T11:52:14.701-0800", 
    "dateString": "2016-02-14T11:52:14.701-0800", 
    "sgv": 102, 
    "device": "xDrip-DexcomShare", 
    "xDrip_filtered": 132, 
    "unfiltered": 147000, 
    "xDrip_raw": 147, 
    "date": 1455479534701, 
    "rssi": 100, 
    "xDrip_calculated_current_slope": 1.9962603389650056e-05, 
    "xDrip_age_adjusted_raw_value": 147, 
    "xDrip_calculated_value": 102
  }, 
  {
    "filtered": 123000, 
    "direction": "FortyFiveUp", 
    "noise": 1, 
    "raw": 110, 
    "type": "sgv", 
    "_id": "56c0d9df07f60885b34476be", 
    "sysTime": "2016-02-14T11:47:14.093-0800", 
    "dateString": "2016-02-14T11:47:14.093-0800", 
    "sgv": 96, 
    "device": "xDrip-DexcomShare", 
    "xDrip_filtered": 123, 
    "unfiltered": 140000, 
    "xDrip_raw": 140, 
    "date": 1455479234093, 
    "rssi": 100, 
    "xDrip_calculated_current_slope": 3.340381538379314e-05, 
    "xDrip_age_adjusted_raw_value": 140, 
    "xDrip_calculated_value": 96
  }, 
  {
    "filtered": 118000, 
    "direction": "Flat", 
    "noise": 1, 
    "raw": 94, 
    "type": "sgv", 
    "_id": "56c0d92207f60885b34476b8", 
    "sysTime": "2016-02-14T11:42:14.726-0800", 
    "dateString": "2016-02-14T11:42:14.726-0800", 
    "sgv": 86, 
    "device": "xDrip-DexcomShare", 
    "xDrip_filtered": 118, 
    "unfiltered": 128000, 
    "xDrip_raw": 128, 
    "date": 1455478934726, 
    "rssi": 100, 
    "xDrip_calculated_current_slope": 2e-05, 
    "xDrip_age_adjusted_raw_value": 128, 
    "xDrip_calculated_value": 86
  }
]